jolieprinter/__init__.py
jolieprinter/printer.py
jolieprinter-0.1.2.dist-info/METADATA
jolieprinter-0.1.2.dist-info/WHEEL
jolieprinter-0.1.2.dist-info/RECORD
