Metadata-Version: 2.1
Name: jolieprinter
Version: 0.1.2
Summary: 
Author: Benedith Mulongo
Author-email: benedith@sunet.se
Requires-Python: >=3.9.15,<4.0.0
Classifier: Programming Language :: Python :: 3
Classifier: Programming Language :: Python :: 3.10
Classifier: Programming Language :: Python :: 3.11
Classifier: Programming Language :: Python :: 3.12
Requires-Dist: numpy (>=2.1.2,<3.0.0)
